xdart/.DS_Store
xdart/__init__.py
xdart/gui/Ui_static.py
xdart/gui/__init__.py
xdart/gui/gui_utils.py
xdart/gui/mainWindow.py
xdart/gui/mainWindow.ui
xdart/gui/static.ui
xdart/gui/tabs/__init__.py
xdart/gui/tabs/static_scan/__init__.py
xdart/gui/tabs/static_scan/display_frame_widget.py
xdart/gui/tabs/static_scan/h5viewer.py
xdart/gui/tabs/static_scan/integrator.py
xdart/gui/tabs/static_scan/metadata.py
xdart/gui/tabs/static_scan/sphere_threads.py
xdart/gui/tabs/static_scan/static_scan_widget.py
xdart/gui/tabs/static_scan/ui/__init__.py
xdart/gui/tabs/static_scan/ui/displayFrameUI.py
xdart/gui/tabs/static_scan/ui/displayFrameUI.ui
xdart/gui/tabs/static_scan/ui/h5viewerUI.py
xdart/gui/tabs/static_scan/ui/h5viewerUI.ui
xdart/gui/tabs/static_scan/ui/integratorUI.py
xdart/gui/tabs/static_scan/ui/integratorUI.ui
xdart/gui/tabs/static_scan/ui/integratorUI_mac.py
xdart/gui/tabs/static_scan/ui/integratorUI_mac.ui
xdart/gui/tabs/static_scan/ui/integratorUI_windows.py
xdart/gui/tabs/static_scan/ui/integratorUI_windows.ui
xdart/gui/tabs/static_scan/ui/staticUI.py
xdart/gui/tabs/static_scan/ui/staticUI.ui
xdart/gui/tabs/static_scan/wranglers/__init__.py
xdart/gui/tabs/static_scan/wranglers/spec_wrangler.py
xdart/gui/tabs/static_scan/wranglers/ui/__init__.py
xdart/gui/tabs/static_scan/wranglers/ui/liveSpecUI.py
xdart/gui/tabs/static_scan/wranglers/ui/liveSpecUI.ui
xdart/gui/tabs/static_scan/wranglers/ui/specUI.py
xdart/gui/tabs/static_scan/wranglers/ui/specUI.ui
xdart/gui/tabs/static_scan/wranglers/wrangler_widget.py
xdart/gui/tabs/ttheta_scan/__init__.py
xdart/gui/tabs/ttheta_scan/displayFrameUI.py
xdart/gui/tabs/ttheta_scan/displayFrameUI.ui
xdart/gui/tabs/ttheta_scan/display_frame_widget.py
xdart/gui/tabs/ttheta_scan/h5viewer.py
xdart/gui/tabs/ttheta_scan/h5viewerUI.py
xdart/gui/tabs/ttheta_scan/h5viewerUI.ui
xdart/gui/tabs/ttheta_scan/integrator.py
xdart/gui/tabs/ttheta_scan/integratorUI.py
xdart/gui/tabs/ttheta_scan/integratorUI.ui
xdart/gui/tabs/ttheta_scan/metadata.py
xdart-0.16.2.dist-info/LICENSE
xdart-0.16.2.dist-info/METADATA
xdart-0.16.2.dist-info/WHEEL
xdart-0.16.2.dist-info/entry_points.txt
xdart-0.16.2.dist-info/RECORD
