Metadata-Version: 2.1
Name: xdart
Version: 0.16.2
Summary: A pyFAI based GUI utility to rebin and visualize X-ray Diffraction data
Home-page: https://github.com/v-thampy/xdart.git
License: MIT
Keywords: xrd,diffracion,pyFAI
Author: Vivek Thampy
Author-email: vthampy@stanford.edu
Requires-Python: >=3.8
Classifier: License :: OSI Approved :: MIT License
Classifier: Programming Language :: Python :: 3
Classifier: Programming Language :: Python :: 3.8
Classifier: Programming Language :: Python :: 3.9
Classifier: Programming Language :: Python :: 3.10
Classifier: Programming Language :: Python :: 3.11
Classifier: Programming Language :: Python :: 3.12
Classifier: Programming Language :: Python :: 3.13
Requires-Dist: fabio
Requires-Dist: h5py
Requires-Dist: hdf5plugin
Requires-Dist: holoviews
Requires-Dist: hvplot
Requires-Dist: icecream
Requires-Dist: imagecodecs
Requires-Dist: ipympl
Requires-Dist: ipywidgets
Requires-Dist: joblib
Requires-Dist: jupyterlab
Requires-Dist: lmfit
Requires-Dist: matplotlib
Requires-Dist: natsort
Requires-Dist: nodejs
Requires-Dist: numpy
Requires-Dist: openpyxl
Requires-Dist: pandas
Requires-Dist: panel
Requires-Dist: pyfai
Requires-Dist: pygix
Requires-Dist: pyqt5
Requires-Dist: pyqtgraph (==0.13.3)
Requires-Dist: pyyaml
Requires-Dist: requests
Requires-Dist: scikit-image
Requires-Dist: scipy
Requires-Dist: seaborn
Requires-Dist: silx
Requires-Dist: xlrd
Requires-Dist: xrayutilities
Project-URL: Documentation, https://github.com/v-thampy/xdart/blob/master/xdart_manual.pdf
Project-URL: Repository, https://github.com/v-thampy/xdart.git
